rfest/__init__.py
rfest/check.py
rfest/generate_test_data.py
rfest/loss.py
rfest/metrics.py
rfest/nonlinearities.py
rfest/priors.py
rfest/simulate.py
rfest/splines.py
rfest/utils.py
rfest/version.py
rfest/EvidenceOpt/__init__.py
rfest/EvidenceOpt/_ald.py
rfest/EvidenceOpt/_ard.py
rfest/EvidenceOpt/_asd.py
rfest/EvidenceOpt/_base.py
rfest/EvidenceOpt/_fasd.py
rfest/EvidenceOpt/_ridge.py
rfest/EvidenceOpt/_sard.py
rfest/GLM/__init__.py
rfest/GLM/_base.py
rfest/GLM/_glm.py
rfest/GLM/_lnln.py
rfest/GLM/_lnp.py
rfest/GLM/_splinelg.py
rfest/GLM/_splinelnln.py
rfest/GLM/_splinelnp.py
rfest/MF/__init__.py
rfest/MF/_initialize.py
rfest/MF/_kmeans.py
rfest/MF/_nmf.py
rfest/MF/_seminmf.py
rfest-2.1.2.dist-info/LICENSE
rfest-2.1.2.dist-info/METADATA
rfest-2.1.2.dist-info/WHEEL
rfest-2.1.2.dist-info/top_level.txt
rfest-2.1.2.dist-info/RECORD
