Metadata-Version: 2.1
Name: rfest
Version: 2.1.2
Summary: Python 3 toolbox for receptive field estimation
Author: Ziwei Huang, Jonathan Oesterle
Author-email: huang-ziwei@outlook.com
Requires-Python: >=3.6
License-File: LICENSE
